cricketapi/__init__.py
cricketapi/py.typed
cricketapi/request_handlers/__init__.py
cricketapi/request_handlers/apis.py
cricketapi-1.0.2.dist-info/METADATA
cricketapi-1.0.2.dist-info/WHEEL
cricketapi-1.0.2.dist-info/top_level.txt
cricketapi-1.0.2.dist-info/RECORD
